{
  "needs": {
    "explicit_needs": [
      "想要遇到更优秀的团队和热爱工作的人",
      "想要完成精妙的作品，创造美好的事情",
      "很想聊聊，很想让自己放松一点",
      "想哭，想畅快地哭出来",
      "渴望被认可，想展示才华",
      "寻求相互理解、相互真诚的伴侣",
      "想慢点走，看看身边的朋友和家人"
    ],
    "implicit_needs": [
      "需要接纳自己的平凡和渺小",
      "需要找回那种敏感的、容易被感动的感受力",
      "需要从理想主义的自我折磨中解放出来",
      "需要不那么着急，允许自己慢慢积累",
      "需要珍惜当下拥有的东西，而不是总想着远方",
      "需要看到自己已经取得的进步",
      "需要允许自己不完美、有缺口",
      "需要真正的休息和放松"
    ],
    "tensions": [
      "理想主义的追求 vs 接纳平凡现实的挣扎",
      "想要优秀、创造美好 vs 感觉自己很渺小、很差劲",
      "渴望关心和连接 vs 刻意回避、封闭自己",
      "想快速达成目标 vs 体会到需要慢慢积累的现实",
      "追求完美 vs 接纳不完美的自己",
      "期待离开现环境寻找更好的 vs 真要离开时的不舍和后悔",
      "用逻辑控制生活 vs 感受到需要体验和感受的呼唤",
      "觉得过去在浪费时间 vs 怀念过去的美好和温柔"
    ],
    "evidence_quotes": [
      "我们原来看过的那些知识让我们感受到人的复杂,但是最近我们有点刻板,把自己对创造美好的期待,不知不觉地投射到了身边朋友身上",
      "我们一方面内心有着汹涌的感情,一方面又让身边的朋友感觉到这个家伙是一个固执、封闭的人。我们总是很着急,着急地想去创造美好的事情",
      "我们内心渴望关心,一方面又在刻意地回避关心",
      "真到了要告别的时候,才体会到身边的朋友是多么友善,在这个团队里有过那么多幸福美好的回忆。曾经觉得粗心、傻乎乎的伙伴,现在细细回想,发现他们都很可爱",
      "我们原来觉得自己的感受是最重要的,即便那时候被别人笑话,我们在图书馆也体会到了一种无法言表的平和与感动。那段时间,我们对一切都心怀感激",
      "我们好像一直在和自己暗暗较劲,自己好辛苦啊。即便不想承认,我们还是很辛苦的"
    ]
  },
  "shining_thoughts": {
    "insights": [
      {
        "summary": "不够好就是足够好",
        "why_it_matters": "这是你在体验失去后得出的珍贵智慧,提醒自己不要总在追求更好中忽略了已经拥有的美好",
        "related_quote": "我们体会到自己对那些有用的东西太习惯了,而不懂得珍惜。不够好就是足够好"
      },
      {
        "summary": "人与人之间的联系在小事上一点点积累,重要的是去做事情、去等待、去相信",
        "why_it_matters": "你看到了关系建立的真相,这比任何技巧都更接近爱的本质",
        "related_quote": "人与人之间的联系,就在这些小事上一点点地积累,重要的是去做事情,去慢慢地等待,去相信"
      },
      {
        "summary": "将理想世界强行投射到物理世界,辛苦的就是自己了",
        "why_it_matters": "这是对自己理想主义倾向非常清醒的觉察,看到了自我折磨的根源",
        "related_quote": "现实世界并非我们想象的那样符合逻辑,如果我们将自己的理想世界强行投射到物理世界,可能辛苦的就是自己了"
      },
      {
        "summary": "怀念和感动的东西,有一部分是曾经承受痛苦和压力的事情",
        "why_it_matters": "你看到了时间赋予经历的力量,理解了当下的困难也会成为未来的养分",
        "related_quote": "好奇怪啊,我们现在怀念和感动的东西,好像一部分是曾经承受痛苦和压力的事情。比如:崇礼越野"
      },
      {
        "summary": "幸福和快乐其实存在于我们自身之中",
        "why_it_matters": "这是在各种比较和焦虑中找到的内在力量,提醒自己幸福不在别处",
        "related_quote": "某种程度上,人与人的差距很大;但某种程度上,在精神和肉体的成长上,大家又是公平的。此刻,我们清晰地感受到,幸福和快乐其实存在于我们自身之中"
      },
      {
        "summary": "接纳自己的缺口,其实是更加智慧的事情",
        "why_it_matters": "你在追求完美的路上看到了另一种可能,这是通向自由的钥匙",
        "related_quote": "宽容、豁达、顺其自然——接纳自己的缺口,其实是更加智慧的事情。现在当然还做不到,但可以一点点积累"
      }
    ],
    "good_questions": [
      {
        "question": "享受创造就一定意味着要不去认识新朋友吗?",
        "comment": "你在质疑自己给自己设置的限制,这个问题本身就在松动那些僵化的信念,很有勇气"
      },
      {
        "question": "我们依靠想象和逻辑思考就能预判现实的事情会如何发生吗?",
        "comment": "这是对自己控制欲的温柔拷问,你已经感受到想象和现实之间的鸿沟,这份清醒很珍贵"
      },
      {
        "question": "我们能为这1%就抛却实实在在体会痛苦、开心、喜悦的那个过程吗?",
        "comment": "你看到了过度理性规划对生命体验的剥夺,这个问题里藏着你对真实生活的渴望"
      },
      {
        "question": "为什么会觉得自己不配拥有幸运和美好呢?",
        "comment": "能够捕捉到这个念头并提出质疑,说明你正在靠近自己内心深处那个需要被看见的声音"
      }
    ],
    "strengths_visible": [
      "具有深刻的自我觉察能力,能看到自己的矛盾和局限",
      "面对真相的勇气,不逃避不把头埋进沙子",
      "长期坚持写作和阅读的习惯,给自己保留了对话的空间",
      "认真做事,在技术上持续积累和进步",
      "发现自己错了就勇敢修正,不固执己见",
      "珍惜关系,能感受到朋友和家人的可贵",
      "在焦虑中仍然保持希望,愿意相信一些事情",
      "从经历中提炼智慧,而不只是抱怨",
      "敏感细腻,能捕捉到生活中的美好细节"
    ]
  },
  "gentle_reflection": {
    "summary_in_friend_tone": "这个月你过得挺不容易的,一边要面对工作转换的决定,一边在和自己的理想主义较劲。你很着急想做出厉害的事情,想遇到优秀的人,但同时又在一次次体会到自己的平凡和渺小,这种落差让你常常觉得难过和焦虑。可贵的是,你没有停止觉察,你看到了自己把理想投射到现实的辛苦,看到了自己对关心的矛盾态度,也看到了在即将失去时才发现身边朋友的可爱。你在这个过程中提炼出了很多智慧:不够好就是足够好、接纳缺口、珍惜体验。你其实已经有了很多进步,也拥有了很多珍贵的东西,只是你对自己太严格了,总觉得自己不够好、很差劲。",
    "soft_reminder": "你知道吗,你一直在说要慢下来、要珍惜、要感受,但同时又那么着急地想证明自己。或许可以试着对自己温柔一点,像对待那个在东农图书馆容易感动的自己一样。那些你觉得浪费的时间、平凡的日子,它们本身就是生活,不需要被证明有意义才配存在。你已经很努力了,真的,允许自己休息一下,允许自己不完美,允许自己就这样存在,这不是放弃,而是真正的勇敢。"
  }
}
